NepTrain/__init__.py
NepTrain/config.ini
NepTrain/utils.py
NepTrain/cli/cli.py
NepTrain/core/__init__.py
NepTrain/core/template.py
NepTrain/core/utils.py
NepTrain/core/gpumd/__init__.py
NepTrain/core/gpumd/io.py
NepTrain/core/gpumd/plot.py
NepTrain/core/gpumd/run.in
NepTrain/core/gpumd/run.py
NepTrain/core/nep/__init__.py
NepTrain/core/nep/io.py
NepTrain/core/nep/plot.py
NepTrain/core/nep/run.py
NepTrain/core/nep/utils.py
NepTrain/core/perturb/__init__.py
NepTrain/core/perturb/_hiphive.py
NepTrain/core/perturb/run.py
NepTrain/core/select/__init__.py
NepTrain/core/select/run.py
NepTrain/core/select/select.py
NepTrain/core/train/__init__.py
NepTrain/core/train/job.yaml
NepTrain/core/train/run.py
NepTrain/core/train/worker.py
NepTrain/core/vasp/INCAR
NepTrain/core/vasp/__init__.py
NepTrain/core/vasp/io.py
NepTrain/core/vasp/run.py
NepTrain-1.4.4.dist-info/LICENSE
NepTrain-1.4.4.dist-info/METADATA
NepTrain-1.4.4.dist-info/WHEEL
NepTrain-1.4.4.dist-info/entry_points.txt
NepTrain-1.4.4.dist-info/top_level.txt
NepTrain-1.4.4.dist-info/RECORD
