Metadata-Version: 2.1
Name: NepTrain
Version: 1.4.4
Summary: NEP自动训练
Author: Chen Cheng bing
Author-email: Chen Cheng bing <1747193328@qq.com>
License:                     GNU GENERAL PUBLIC LICENSE
Project-URL: Homepage, https://github.com/aboys-cb/NepTrain
Project-URL: Documentation, https://github.com/aboys-cb/NepTrain
Project-URL: Repository, https://github.com/aboys-cb/NepTrain
Project-URL: Issues, https://github.com/aboys-cb/NepTrain/issues
Classifier: Development Status :: 4 - Beta
Classifier: Intended Audience :: Science/Research
Classifier: Operating System :: OS Independent
Classifier: Programming Language :: Python :: 3
Classifier: Programming Language :: Python :: 3.10
Classifier: Programming Language :: Python :: 3.11
Classifier: Programming Language :: Python :: 3.12
Classifier: Topic :: Scientific/Engineering :: Chemistry
Classifier: Topic :: Scientific/Engineering :: Information Analysis
Classifier: Topic :: Scientific/Engineering :: Physics
Classifier: Topic :: Software Development :: Libraries :: Python Modules
Requires-Python: <3.13,>=3.8
License-File: LICENSE
Requires-Dist: ase>=3.23.0
Requires-Dist: rich
Requires-Dist: argcomplete
Requires-Dist: watchdog
Requires-Dist: scikit-learn
Requires-Dist: calorine>=3.0
Requires-Dist: ruamel.yaml
Requires-Dist: dscribe
Requires-Dist: umap-learn>=0.5.7
